tagbiljett/__init__.py
tagbiljett/__main__.py
tagbiljett/tagbiljett.py
tagbiljett-0.1.2.dist-info/LICENSE
tagbiljett-0.1.2.dist-info/METADATA
tagbiljett-0.1.2.dist-info/WHEEL
tagbiljett-0.1.2.dist-info/entry_points.txt
tagbiljett-0.1.2.dist-info/top_level.txt
tagbiljett-0.1.2.dist-info/RECORD
