Metadata-Version: 2.1
Name: tagbiljett
Version: 0.1.2
Summary: A command-line tool for querying SJ ticket prices
Author-email: Jonas Windhager <jonas@windhager.io>
License: MIT License
Requires-Python: >=3.9
License-File: LICENSE
Requires-Dist: click
Requires-Dist: pandas
Requires-Dist: requests
